barebones_rpg/__init__.py
barebones_rpg/combat/__init__.py
barebones_rpg/combat/actions.py
barebones_rpg/combat/combat.py
barebones_rpg/combat/damage_types.py
barebones_rpg/combat/targeting.py
barebones_rpg/core/__init__.py
barebones_rpg/core/events.py
barebones_rpg/core/game.py
barebones_rpg/core/registry.py
barebones_rpg/core/save_manager.py
barebones_rpg/core/serialization.py
barebones_rpg/core/singleton.py
barebones_rpg/dialog/__init__.py
barebones_rpg/dialog/dialog.py
barebones_rpg/dialog/dialog_renderer.py
barebones_rpg/entities/__init__.py
barebones_rpg/entities/ai.py
barebones_rpg/entities/ai_interface.py
barebones_rpg/entities/entity.py
barebones_rpg/entities/stats.py
barebones_rpg/examples/__init__.py
barebones_rpg/examples/custom_ai_example.py
barebones_rpg/examples/mini_rpg.py
barebones_rpg/examples/save_load_example.py
barebones_rpg/examples/simple_combat_example.py
barebones_rpg/examples/tile_based_example.py
barebones_rpg/items/__init__.py
barebones_rpg/items/inventory.py
barebones_rpg/items/item.py
barebones_rpg/items/loot.py
barebones_rpg/items/loot_manager.py
barebones_rpg/loaders/__init__.py
barebones_rpg/loaders/data_loader.py
barebones_rpg/party/__init__.py
barebones_rpg/party/party.py
barebones_rpg/quests/__init__.py
barebones_rpg/quests/quest.py
barebones_rpg/rendering/__init__.py
barebones_rpg/rendering/click_to_move.py
barebones_rpg/rendering/pygame_renderer.py
barebones_rpg/rendering/renderer.py
barebones_rpg/rendering/tile_renderer.py
barebones_rpg/rendering/ui_components.py
barebones_rpg/world/__init__.py
barebones_rpg/world/action_points.py
barebones_rpg/world/tilemap_pathfinding.py
barebones_rpg/world/world.py
barebones_rpg-0.2.0.dist-info/METADATA
barebones_rpg-0.2.0.dist-info/WHEEL
barebones_rpg-0.2.0.dist-info/licenses/LICENSE.md
barebones_rpg-0.2.0.dist-info/RECORD
