Metadata-Version: 2.4
Name: barebones-rpg
Version: 0.2.0
Summary: A flexible, code-first RPG framework for building turn-based games with support for procedural generation and AI-driven content
Project-URL: Homepage, https://github.com/piercegov/barebones_rpg
Project-URL: Documentation, https://piercegov.github.io/barebones_rpg/
Project-URL: Repository, https://github.com/piercegov/barebones_rpg
Project-URL: Bug Tracker, https://github.com/piercegov/barebones_rpg/issues
Author-email: Pierce Governale <piercegovernale@gmail.com>
License: MIT
License-File: LICENSE.md
Keywords: framework,game,game-development,procedural-generation,pygame,rpg,turn-based
Classifier: Development Status :: 3 - Alpha
Classifier: Intended Audience :: Developers
Classifier: License :: OSI Approved :: MIT License
Classifier: Programming Language :: Python :: 3
Classifier: Programming Language :: Python :: 3.11
Classifier: Programming Language :: Python :: 3.12
Classifier: Topic :: Games/Entertainment :: Role-Playing
Classifier: Topic :: Software Development :: Libraries :: Application Frameworks
Classifier: Topic :: Software Development :: Libraries :: pygame
Requires-Python: >=3.11
Requires-Dist: pydantic>=2.0.0
Requires-Dist: pygame>=2.5.0
Requires-Dist: pyyaml>=6.0
Provides-Extra: dev
Requires-Dist: black>=23.0.0; extra == 'dev'
Requires-Dist: mypy>=1.0.0; extra == 'dev'
Requires-Dist: pytest-cov>=4.0.0; extra == 'dev'
Requires-Dist: pytest>=7.0.0; extra == 'dev'
Provides-Extra: docs
Requires-Dist: furo>=2023.0.0; extra == 'docs'
Requires-Dist: myst-parser>=2.0.0; extra == 'docs'
Requires-Dist: sphinx-autodoc-typehints>=1.24.0; extra == 'docs'
Requires-Dist: sphinx>=7.0.0; extra == 'docs'
